{
  "text_elements": [
    {
      "entity_id": "static_text_46e65f49",
      "x": 15,
      "y": 15,
      "font_size": 25,
      "color": [
        0,
        0,
        255
      ],
      "alignment": 0,
      "prefix": "",
      "suffix": "",
      "format": "{value}",
      "font_path": "/config/custom_components/uart_time_sender/fonts/MaterialIcons-Regular.ttf",
      "is_static": true,
      "static_value": "mdi:television-ambient-light"
    }
  ],
  "display_config": {
    "background_image_landscape": "/config/custom_components/uart_time_sender/AceMagic_LANDSCAPE.png",
    "background_image_portrait": "/config/custom_components/uart_time_sender/AceMagic_PORTRAIT.png",
    "last_orientation": 1
  }
}